func2json/__init__.py
func2json/func2json.py
func2json-0.1.3.dist-info/METADATA
func2json-0.1.3.dist-info/WHEEL
func2json-0.1.3.dist-info/top_level.txt
func2json-0.1.3.dist-info/RECORD
