Metadata-Version: 2.1
Name: func2json
Version: 0.1.3
Summary: Convert Python functions to JSON schemas using Pydantic, Compatible with LLM Function Calling.
Home-page: https://github.com/ThanabordeeN/func2json
Author: Thanabordee Noun.
Author-email: thanabordee.noun@gmail.com
Classifier: Programming Language :: Python :: 3
Classifier: License :: OSI Approved :: MIT License
Classifier: Operating System :: OS Independent
Requires-Dist: pydantic
Requires-Dist: docstring_parser
